frekil/__init__.py
frekil/client.py
frekil/api/__init__.py
frekil/api/allocations.py
frekil/api/base.py
frekil/api/projects.py
frekil/auth/__init__.py
frekil/auth/api_key.py
frekil/exceptions/__init__.py
frekil/exceptions/base.py
frekil/utils/__init__.py
frekil/utils/helpers.py
frekil-0.1.9.dist-info/licenses/LICENSE
frekil-0.1.9.dist-info/METADATA
frekil-0.1.9.dist-info/WHEEL
frekil-0.1.9.dist-info/top_level.txt
frekil-0.1.9.dist-info/RECORD
