Metadata-Version: 2.4
Name: frekil
Version: 0.1.9
Summary: Official Python SDK for Frekil API
Author-email: Notate <support@notatehq.com>
License: MIT
Project-URL: Homepage, https://notatehq.com
Project-URL: Documentation, https://notatehq.com/docs
Project-URL: Repository, https://github.com/notatehq/frekil-python-sdk
Project-URL: Issues, https://github.com/notatehq/frekil-python-sdk/issues
Keywords: frekil,sdk,api,notate,medical,imaging
Classifier: Programming Language :: Python :: 3
Classifier: Programming Language :: Python :: 3.7
Classifier: Programming Language :: Python :: 3.8
Classifier: Programming Language :: Python :: 3.9
Classifier: Programming Language :: Python :: 3.10
Classifier: License :: OSI Approved :: MIT License
Classifier: Operating System :: OS Independent
Classifier: Development Status :: 4 - Beta
Classifier: Intended Audience :: Developers
Classifier: Topic :: Software Development :: Libraries :: Python Modules
Requires-Python: >=3.10
License-File: LICENSE
Requires-Dist: requests>=2.25.0
Dynamic: license-file
